plexiglas/__init__.py
plexiglas/cli.py
plexiglas/content.py
plexiglas/db.py
plexiglas/db_migrations.py
plexiglas/keyring_stub.py
plexiglas/mobile_sync.py
plexiglas/plex.py
plexiglas/plugin.py
plexiglas/simple_sync.py
plexiglas/token_bucket.py
plexiglas/tqdm_stub.py
plexiglas-0.4.4.dist-info/LICENSE
plexiglas-0.4.4.dist-info/METADATA
plexiglas-0.4.4.dist-info/WHEEL
plexiglas-0.4.4.dist-info/entry_points.txt
plexiglas-0.4.4.dist-info/top_level.txt
plexiglas-0.4.4.dist-info/RECORD
