Metadata-Version: 2.1
Name: plexiglas
Version: 0.4.4
Summary: Tool for downloading videos from your Plex server to an external HDD
Home-page: https://github.com/andrey-yantsen/plexiglass
Author: Andrey Yantsen
Author-email: andrey@janzen.su
License: MIT
Platform: UNKNOWN
Classifier: Development Status :: 4 - Beta
Classifier: Intended Audience :: End Users/Desktop
Classifier: License :: OSI Approved :: MIT License
Classifier: Programming Language :: Python :: 2
Classifier: Programming Language :: Python :: 2.7
Classifier: Programming Language :: Python :: 3
Requires-Dist: argon2-cffi
Requires-Dist: certifi
Requires-Dist: cffi
Requires-Dist: chardet
Requires-Dist: configparser
Requires-Dist: entrypoints
Requires-Dist: enum34
Requires-Dist: humanfriendly
Requires-Dist: idna
Requires-Dist: keyring
Requires-Dist: keyrings.cryptfile
Requires-Dist: monotonic
Requires-Dist: plexapi
Requires-Dist: pycparser
Requires-Dist: pycryptodome
Requires-Dist: requests
Requires-Dist: six
Requires-Dist: tqdm
Requires-Dist: urllib3
Requires-Dist: websocket-client
